atcnoseplugin/__init__.py
atcnoseplugin/category.py
atcnoseplugin/fileoutput.py
atcnoseplugin/planloader.py
atcnoseplugin/tools.py
atcnoseplugin-0.1.1.dist-info/METADATA
atcnoseplugin-0.1.1.dist-info/WHEEL
atcnoseplugin-0.1.1.dist-info/entry_points.txt
atcnoseplugin-0.1.1.dist-info/top_level.txt
atcnoseplugin-0.1.1.dist-info/RECORD
