Metadata-Version: 2.1
Name: atcnoseplugin
Version: 0.1.1
Summary: test plugins for exec related plan based on nosetests
Home-page: UNKNOWN
Author: thomas.ning
Author-email: ningruhu@163.com
License: MIT
Platform: UNKNOWN
